environs/__init__.py
environs/exceptions.py
environs/fields.py
environs/py.typed
environs/types.py
environs-13.0.0.dist-info/LICENSE
environs-13.0.0.dist-info/WHEEL
environs-13.0.0.dist-info/METADATA
environs-13.0.0.dist-info/RECORD
