Metadata-Version: 2.3
Name: environs
Version: 13.0.0
Summary: simplified environment variable parsing
Author-email: Steven Loria <sloria1@gmail.com>
Requires-Python: >=3.9
Classifier: Intended Audience :: Developers
Classifier: License :: OSI Approved :: MIT License
Classifier: Natural Language :: English
Classifier: Programming Language :: Python :: 3
Classifier: Programming Language :: Python :: 3.9
Classifier: Programming Language :: Python :: 3.10
Classifier: Programming Language :: Python :: 3.11
Classifier: Programming Language :: Python :: 3.12
Classifier: Programming Language :: Python :: 3.13
Requires-Dist: python-dotenv
Requires-Dist: marshmallow>=3.18.0
Requires-Dist: typing-extensions; python_version < '3.11'
Requires-Dist: environs[tests] ; extra == "dev"
Requires-Dist: tox ; extra == "dev"
Requires-Dist: pre-commit>=4.0,<5.0 ; extra == "dev"
Requires-Dist: dj-database-url ; extra == "django"
Requires-Dist: dj-email-url ; extra == "django"
Requires-Dist: django-cache-url ; extra == "django"
Requires-Dist: environs[django] ; extra == "tests"
Requires-Dist: pytest ; extra == "tests"
Requires-Dist: packaging ; extra == "tests"
Project-URL: Changelog, https://github.com/sloria/environs/blob/master/CHANGELOG.md
Project-URL: Issues, https://github.com/sloria/environs/issues
Project-URL: Source, https://github.com/sloria/environs
Provides-Extra: dev
Provides-Extra: django
Provides-Extra: tests
